{
  "recommended_threshold": 0.05,
  "optimization_criterion": "F2-score (Recall \uc911\uc2dc)",
  "test_performance": {
    "roc_auc": 0.628338568139523,
    "pr_auc": 0.002117212214980297,
    "precision": 0.003745318352059925,
    "recall": 0.09090909090909091,
    "f1": 0.007194244604316547,
    "f2": 0.01607717041800643,
    "true_positives": 1,
    "false_positives": 266,
    "false_negatives": 10,
    "true_negatives": 12093
  },
  "scenarios": {
    "aggressive": {
      "threshold": 0.05,
      "recall": 0.09090909090909091,
      "precision": 0.003745318352059925
    },
    "balanced": {
      "threshold": 0.05,
      "f1": 0.007194244604316547
    },
    "conservative": {
      "threshold": 0.05,
      "precision": 0.003745318352059925
    }
  },
  "all_thresholds": [
    {
      "threshold": 0.05,
      "precision": 0.003745318352059925,
      "recall": 0.09090909090909091,
      "f1": 0.007194244604316547,
      "f2": 0.01607717041800643,
      "f0.5": 0.004633920296570899,
      "tp": 1,
      "fp": 266,
      "fn": 10,
      "tn": 12093
    },
    {
      "threshold": 0.1,
      "precision": 0.0,
      "recall": 0.0,
      "f1": 0.0,
      "f2": 0.0,
      "f0.5": 0.0,
      "tp": 0,
      "fp": 102,
      "fn": 11,
      "tn": 12257
    },
    {
      "threshold": 0.15000000000000002,
      "precision": 0.0,
      "recall": 0.0,
      "f1": 0.0,
      "f2": 0.0,
      "f0.5": 0.0,
      "tp": 0,
      "fp": 42,
      "fn": 11,
      "tn": 12317
    },
    {
      "threshold": 0.2,
      "precision": 0.0,
      "recall": 0.0,
      "f1": 0.0,
      "f2": 0.0,
      "f0.5": 0.0,
      "tp": 0,
      "fp": 22,
      "fn": 11,
      "tn": 12337
    },
    {
      "threshold": 0.25,
      "precision": 0.0,
      "recall": 0.0,
      "f1": 0.0,
      "f2": 0.0,
      "f0.5": 0.0,
      "tp": 0,
      "fp": 14,
      "fn": 11,
      "tn": 12345
    },
    {
      "threshold": 0.3,
      "precision": 0.0,
      "recall": 0.0,
      "f1": 0.0,
      "f2": 0.0,
      "f0.5": 0.0,
      "tp": 0,
      "fp": 10,
      "fn": 11,
      "tn": 12349
    },
    {
      "threshold": 0.35000000000000003,
      "precision": 0.0,
      "recall": 0.0,
      "f1": 0.0,
      "f2": 0.0,
      "f0.5": 0.0,
      "tp": 0,
      "fp": 6,
      "fn": 11,
      "tn": 12353
    },
    {
      "threshold": 0.4,
      "precision": 0.0,
      "recall": 0.0,
      "f1": 0.0,
      "f2": 0.0,
      "f0.5": 0.0,
      "tp": 0,
      "fp": 4,
      "fn": 11,
      "tn": 12355
    },
    {
      "threshold": 0.45,
      "precision": 0.0,
      "recall": 0.0,
      "f1": 0.0,
      "f2": 0.0,
      "f0.5": 0.0,
      "tp": 0,
      "fp": 3,
      "fn": 11,
      "tn": 12356
    },
    {
      "threshold": 0.5,
      "precision": 0.0,
      "recall": 0.0,
      "f1": 0.0,
      "f2": 0.0,
      "f0.5": 0.0,
      "tp": 0,
      "fp": 3,
      "fn": 11,
      "tn": 12356
    },
    {
      "threshold": 0.55,
      "precision": 0.0,
      "recall": 0.0,
      "f1": 0.0,
      "f2": 0.0,
      "f0.5": 0.0,
      "tp": 0,
      "fp": 2,
      "fn": 11,
      "tn": 12357
    },
    {
      "threshold": 0.6000000000000001,
      "precision": 0.0,
      "recall": 0.0,
      "f1": 0.0,
      "f2": 0.0,
      "f0.5": 0.0,
      "tp": 0,
      "fp": 1,
      "fn": 11,
      "tn": 12358
    },
    {
      "threshold": 0.6500000000000001,
      "precision": 0.0,
      "recall": 0.0,
      "f1": 0.0,
      "f2": 0.0,
      "f0.5": 0.0,
      "tp": 0,
      "fp": 1,
      "fn": 11,
      "tn": 12358
    },
    {
      "threshold": 0.7000000000000001,
      "precision": 0.0,
      "recall": 0.0,
      "f1": 0.0,
      "f2": 0.0,
      "f0.5": 0.0,
      "tp": 0,
      "fp": 0,
      "fn": 11,
      "tn": 12359
    },
    {
      "threshold": 0.7500000000000001,
      "precision": 0.0,
      "recall": 0.0,
      "f1": 0.0,
      "f2": 0.0,
      "f0.5": 0.0,
      "tp": 0,
      "fp": 0,
      "fn": 11,
      "tn": 12359
    },
    {
      "threshold": 0.8,
      "precision": 0.0,
      "recall": 0.0,
      "f1": 0.0,
      "f2": 0.0,
      "f0.5": 0.0,
      "tp": 0,
      "fp": 0,
      "fn": 11,
      "tn": 12359
    },
    {
      "threshold": 0.8500000000000001,
      "precision": 0.0,
      "recall": 0.0,
      "f1": 0.0,
      "f2": 0.0,
      "f0.5": 0.0,
      "tp": 0,
      "fp": 0,
      "fn": 11,
      "tn": 12359
    },
    {
      "threshold": 0.9000000000000001,
      "precision": 0.0,
      "recall": 0.0,
      "f1": 0.0,
      "f2": 0.0,
      "f0.5": 0.0,
      "tp": 0,
      "fp": 0,
      "fn": 11,
      "tn": 12359
    }
  ]
}